bread_inspektor/__init__.py
bread_inspektor/constants.py
bread_inspektor/file_utils.py
bread_inspektor/main.py
bread_inspektor/rules.py
bread_inspektor/validator.py
bread_inspektor-0.1.dev71.dist-info/LICENSE
bread_inspektor-0.1.dev71.dist-info/METADATA
bread_inspektor-0.1.dev71.dist-info/WHEEL
bread_inspektor-0.1.dev71.dist-info/entry_points.txt
bread_inspektor-0.1.dev71.dist-info/top_level.txt
bread_inspektor-0.1.dev71.dist-info/RECORD
