Metadata-Version: 2.1
Name: bread_inspektor
Version: 0.1.dev71
Summary: A tool to help SBOs validate BEAD Challenge Process data files before submission to NTIA.
Author-email: Nick Ross <tspread@uchicago.edu>, Matt Triano <matthewtriano@uchicago.edu>
Maintainer: Matt Triano, Nick Ross
Classifier: Programming Language :: Python :: 3
Classifier: Operating System :: OS Independent
Requires-Python: >=3.8
License-File: LICENSE
Provides-Extra: dev
Requires-Dist: flake8 ; extra == 'dev'
Requires-Dist: twine ; extra == 'dev'
Requires-Dist: tox >=4.0 ; extra == 'dev'
Requires-Dist: black ; extra == 'dev'
Requires-Dist: isort ; extra == 'dev'
Requires-Dist: pytest >=6.0 ; extra == 'dev'
Requires-Dist: pytest-cov ; extra == 'dev'
